{"IdMatch": "21908", "IdStage": "4655", "IdGroup": "4657", "IdSeason": "4654", "IdCompetition": "103", "CompetitionName": [{"Locale": "en-GB", "Description": "FIFA Women's World Cup\u2122"}], "SeasonName": [{"Locale": "en-GB", "Description": "FIFA Women's World Cup Sweden 1995"}], "SeasonShortName": [{"Locale": "en-GB", "Description": "Sweden 1995"}], "Stadium": {"IdStadium": "5001904", "Name": [{"Locale": "en-GB", "Description": "Tingvalla"}], "Capacity": null, "WebAddress": null, "Built": null, "Roof": false, "Turf": null, "IdCity": "1786", "CityName": [{"Locale": "en-GB", "Description": "Karlstad"}], "IdCountry": "SWE", "PostalCode": null, "Street": null, "Email": null, "Fax": null, "Phone": null, "AffiliationCountry": null, "AffiliationRegion": null, "Latitude": null, "Longitude": null, "Length": null, "Width": null, "Properties": {"IdIFES": "5001904"}, "IsUpdateable": null}, "ResultType": 1, "MatchDay": null, "HomeTeamPenaltyScore": null, "AwayTeamPenaltyScore": null, "AggregateHomeTeamScore": null, "AggregateAwayTeamScore": null, "Weather": null, "Attendance": "4344", "Date": "1995-06-06T17:00:00Z", "LocalDate": "1995-06-06T19:00:00Z", "MatchTime": null, "SecondHalfTime": null, "FirstHalfTime": null, "FirstHalfExtraTime": null, "SecondHalfExtraTime": null, "Winner": "1882882", "Period": 10, "HomeTeam": {"Score": 8, "Side": null, "IdTeam": "1882882", "PictureUrl": "https://api.fifa.com/api/v1/picture/flags-{format}-{size}/NOR", "IdCountry": "NOR", "TeamType": 1, "AgeType": 7, "Tactics": null, "TeamName": [{"Locale": "en-GB", "Description": "Norway"}], "Abbreviation": "NOR", "Coaches": [{"IdCoach": "183097", "IdCountry": "NOR", "Name": [{"Locale": "en-GB", "Description": "PELLERUD Even"}], "Alias": [{"Locale": "en-GB", "Description": "Even PELLERUD"}], "Role": 0}], "Players": [{"IdPlayer": "214", "IdTeam": "1882882", "ShirtNumber": 1, "Status": 1, "SpecialStatus": null, "Captain": false, "PlayerName": [{"Locale": "en-GB", "Description": "Bente NORDBY"}], "ShortName": [{"Locale": "en-GB", "Description": "B. NORDBY"}], "Position": 0, "FieldStatus": 0, "LineupX": null, "LineupY": null}, {"IdPlayer": "532", "IdTeam": "1882882", "ShirtNumber": 2, "Status": 1, "SpecialStatus": null, "Captain": false, "PlayerName": [{"Locale": "en-GB", "Description": "Tina SVENSSON"}], "ShortName": [{"Locale": "en-GB", "Description": "Tina SVENSSON"}], "Position": 1, "FieldStatus": 0, "LineupX": null, "LineupY": null}, {"IdPlayer": "512", "IdTeam": "1882882", "ShirtNumber": 3, "Status": 1, "SpecialStatus": null, "Captain": false, "PlayerName": [{"Locale": "en-GB", "Description": "Gro ESPESETH"}], "ShortName": [{"Locale": "en-GB", "Description": "ESPESETH"}], "Position": 1, "FieldStatus": 0, "LineupX": null, "LineupY": null}, {"IdPlayer": "168095", "IdTeam": "1882882", "ShirtNumber": 4, "Status": 1, "SpecialStatus": null, "Captain": false, "PlayerName": [{"Locale": "en-GB", "Description": "Anne NYMARK ANDERSEN"}], "ShortName": [{"Locale": "en-GB", "Description": "Anne NYMARK ANDERSEN"}], "Position": 2, "FieldStatus": 0, "LineupX": null, "LineupY": null}, {"IdPlayer": "523", "IdTeam": "1882882", "ShirtNumber": 13, "Status": 1, "SpecialStatus": null, "Captain": false, "PlayerName": [{"Locale": "en-GB", "Description": "Merete MYKLEBUST"}], "ShortName": [{"Locale": "en-GB", "Description": "Merete MYKLEBUST"}], "Position": 1, "FieldStatus": 0, "LineupX": null, "LineupY": null}, {"IdPlayer": "218", "IdTeam": "1882882", "ShirtNumber": 6, "Status": 1, "SpecialStatus": null, "Captain": false, "PlayerName": [{"Locale": "en-GB", "Description": "Hege RIISE"}], "ShortName": [{"Locale": "en-GB", "Description": "RIISE"}], "Position": 2, "FieldStatus": 0, "LineupX": null, "LineupY": null}, {"IdPlayer": "530", "IdTeam": "1882882", "ShirtNumber": 8, "Status": 1, "SpecialStatus": null, "Captain": false, "PlayerName": [{"Locale": "en-GB", "Description": "Heidi STOERE"}], "ShortName": [{"Locale": "en-GB", "Description": "Heidi STOERE"}], "Position": 2, "FieldStatus": 0, "LineupX": null, "LineupY": null}, {"IdPlayer": "515", "IdTeam": "1882882", "ShirtNumber": 7, "Status": 1, "SpecialStatus": null, "Captain": false, "PlayerName": [{"Locale": "en-GB", "Description": "Tone HAUGEN"}], "ShortName": [{"Locale": "en-GB", "Description": "Tone HAUGEN"}], "Position": 2, "FieldStatus": 0, "LineupX": null, "LineupY": null}, {"IdPlayer": "527", "IdTeam": "1882882", "ShirtNumber": 9, "Status": 1, "SpecialStatus": null, "Captain": false, "PlayerName": [{"Locale": "en-GB", "Description": "Kristin SANDBERG"}], "ShortName": [{"Locale": "en-GB", "Description": "Kristin SANDBERG"}], "Position": 3, "FieldStatus": 0, "LineupX": null, "LineupY": null}, {"IdPlayer": "212", "IdTeam": "1882882", "ShirtNumber": 10, "Status": 1, "SpecialStatus": null, "Captain": false, "PlayerName": [{"Locale": "en-GB", "Description": "Linda MEDALEN"}], "ShortName": [{"Locale": "en-GB", "Description": "Linda MEDALEN"}], "Position": 3, "FieldStatus": 0, "LineupX": null, "LineupY": null}, {"IdPlayer": "162904", "IdTeam": "1882882", "ShirtNumber": 11, "Status": 1, "SpecialStatus": null, "Captain": false, "PlayerName": [{"Locale": "en-GB", "Description": "Ann Kristin AARONES"}], "ShortName": [{"Locale": "en-GB", "Description": "Ann Kristin AARONES"}], "Position": 3, "FieldStatus": 0, "LineupX": null, "LineupY": null}, {"IdPlayer": "526", "IdTeam": "1882882", "ShirtNumber": 5, "Status": 2, "SpecialStatus": null, "Captain": false, "PlayerName": [{"Locale": "en-GB", "Description": "Nina NYMARK ANDERSEN"}], "ShortName": [{"Locale": "en-GB", "Description": "Nina NYMARK ANDERSEN"}], "Position": 1, "FieldStatus": 0, "LineupX": null, "LineupY": null}, {"IdPlayer": "529", "IdTeam": "1882882", "ShirtNumber": 12, "Status": 2, "SpecialStatus": null, "Captain": false, "PlayerName": [{"Locale": "en-GB", "Description": "Reidun SETH"}], "ShortName": [{"Locale": "en-GB", "Description": "Reidun SETH"}], "Position": 0, "FieldStatus": 0, "LineupX": null, "LineupY": null}, {"IdPlayer": "514", "IdTeam": "1882882", "ShirtNumber": 14, "Status": 2, "SpecialStatus": null, "Captain": false, "PlayerName": [{"Locale": "en-GB", "Description": "Hege GUNNEROD"}], "ShortName": [{"Locale": "en-GB", "Description": "Hege GUNNEROD"}], "Position": 2, "FieldStatus": 0, "LineupX": null, "LineupY": null}, {"IdPlayer": "522", "IdTeam": "1882882", "ShirtNumber": 15, "Status": 2, "SpecialStatus": null, "Captain": false, "PlayerName": [{"Locale": "en-GB", "Description": "Randi LEINAN"}], "ShortName": [{"Locale": "en-GB", "Description": "Randi LEINAN"}], "Position": 3, "FieldStatus": 0, "LineupX": null, "LineupY": null}, {"IdPlayer": "216", "IdTeam": "1882882", "ShirtNumber": 16, "Status": 2, "SpecialStatus": null, "Captain": false, "PlayerName": [{"Locale": "en-GB", "Description": "Marianne PETTERSEN"}], "ShortName": [{"Locale": "en-GB", "Description": "PETTERSEN"}], "Position": 3, "FieldStatus": 0, "LineupX": null, "LineupY": null}, {"IdPlayer": "181217", "IdTeam": "1882882", "ShirtNumber": 17, "Status": 2, "SpecialStatus": null, "Captain": false, "PlayerName": [{"Locale": "en-GB", "Description": "Anita WAAGE"}], "ShortName": [{"Locale": "en-GB", "Description": "Anita WAAGE"}], "Position": 1, "FieldStatus": 0, "LineupX": null, "LineupY": null}, {"IdPlayer": "204", "IdTeam": "1882882", "ShirtNumber": 18, "Status": 2, "SpecialStatus": null, "Captain": false, "PlayerName": [{"Locale": "en-GB", "Description": "Tone Gunn FRUSTOL"}], "ShortName": [{"Locale": "en-GB", "Description": "Tone Gunn FRUSTOL"}], "Position": 2, "FieldStatus": 0, "LineupX": null, "LineupY": null}, {"IdPlayer": "511", "IdTeam": "1882882", "ShirtNumber": 19, "Status": 2, "SpecialStatus": null, "Captain": false, "PlayerName": [{"Locale": "en-GB", "Description": "Agnete CARLSEN"}], "ShortName": [{"Locale": "en-GB", "Description": "Agnete CARLSEN"}], "Position": 1, "FieldStatus": 0, "LineupX": null, "LineupY": null}, {"IdPlayer": "181218", "IdTeam": "1882882", "ShirtNumber": 20, "Status": 2, "SpecialStatus": null, "Captain": false, "PlayerName": [{"Locale": "en-GB", "Description": "Ingrid STERNHOFF"}], "ShortName": [{"Locale": "en-GB", "Description": "Ingrid STERNHOFF"}], "Position": 0, "FieldStatus": 0, "LineupX": null, "LineupY": null}], "Bookings": [], "Goals": [{"Type": 2, "IdPlayer": "527", "Minute": "30'", "IdAssistPlayer": null, "Period": 3, "IdGoal": null, "IdTeam": "1882882"}, {"Type": 2, "IdPlayer": "527", "Minute": "44'", "IdAssistPlayer": null, "Period": 3, "IdGoal": null, "IdTeam": "1882882"}, {"Type": 2, "IdPlayer": "218", "Minute": "49'", "IdAssistPlayer": null, "Period": 5, "IdGoal": null, "IdTeam": "1882882"}, {"Type": 2, "IdPlayer": "162904", "Minute": "60'", "IdAssistPlayer": null, "Period": 5, "IdGoal": null, "IdTeam": "1882882"}, {"Type": 2, "IdPlayer": "212", "Minute": "67'", "IdAssistPlayer": null, "Period": 5, "IdGoal": null, "IdTeam": "1882882"}, {"Type": 1, "IdPlayer": "532", "Minute": "76'", "IdAssistPlayer": null, "Period": 5, "IdGoal": null, "IdTeam": "1882882"}, {"Type": 2, "IdPlayer": "527", "Minute": "82'", "IdAssistPlayer": null, "Period": 5, "IdGoal": null, "IdTeam": "1882882"}, {"Type": 2, "IdPlayer": "162904", "Minute": "90'", "IdAssistPlayer": null, "Period": 5, "IdGoal": null, "IdTeam": "1882882"}], "Substitutions": [{"IdEvent": null, "Period": 5, "Reason": 0, "SubstitutePosition": 2, "IdPlayerOff": "530", "IdPlayerOn": "216", "PlayerOffName": [{"Locale": "en-GB", "Description": "Heidi STOERE"}], "PlayerOnName": [{"Locale": "en-GB", "Description": "Marianne PETTERSEN"}], "Minute": "55'", "IdTeam": "1882882"}, {"IdEvent": null, "Period": 5, "Reason": 0, "SubstitutePosition": 2, "IdPlayerOff": "218", "IdPlayerOn": "204", "PlayerOffName": [{"Locale": "en-GB", "Description": "Hege RIISE"}], "PlayerOnName": [{"Locale": "en-GB", "Description": "Tone Gunn FRUSTOL"}], "Minute": "69'", "IdTeam": "1882882"}, {"IdEvent": null, "Period": 5, "Reason": 0, "SubstitutePosition": 2, "IdPlayerOff": "168095", "IdPlayerOn": "526", "PlayerOffName": [{"Locale": "en-GB", "Description": "Anne NYMARK ANDERSEN"}], "PlayerOnName": [{"Locale": "en-GB", "Description": "Nina NYMARK ANDERSEN"}], "Minute": "77'", "IdTeam": "1882882"}], "FootballType": 0, "Gender": 2, "IdAssociation": "NOR"}, "AwayTeam": {"Score": 0, "Side": null, "IdTeam": "1882893", "PictureUrl": "https://api.fifa.com/api/v1/picture/flags-{format}-{size}/NGA", "IdCountry": "NGA", "TeamType": 1, "AgeType": 7, "Tactics": null, "TeamName": [{"Locale": "en-GB", "Description": "Nigeria"}], "Abbreviation": "NGA", "Coaches": [{"IdCoach": "286448", "IdCountry": "NGA", "Name": [{"Locale": "en-GB", "Description": "HAMILTON Paul"}], "Alias": [{"Locale": "en-GB", "Description": "Paul HAMILTON"}], "Role": 0}], "Players": [{"IdPlayer": "182", "IdTeam": "1882893", "ShirtNumber": 1, "Status": 1, "SpecialStatus": null, "Captain": false, "PlayerName": [{"Locale": "en-GB", "Description": "Ann CHIEJINE"}], "ShortName": [{"Locale": "en-GB", "Description": "CHIEJINE A."}], "Position": 0, "FieldStatus": 0, "LineupX": null, "LineupY": null}, {"IdPlayer": "195", "IdTeam": "1882893", "ShirtNumber": 10, "Status": 1, "SpecialStatus": null, "Captain": false, "PlayerName": [{"Locale": "en-GB", "Description": "Mavis OGUN"}], "ShortName": [{"Locale": "en-GB", "Description": "Mavis OGUN"}], "Position": 1, "FieldStatus": 0, "LineupX": null, "LineupY": null}, {"IdPlayer": "499", "IdTeam": "1882893", "ShirtNumber": 14, "Status": 1, "SpecialStatus": null, "Captain": false, "PlayerName": [{"Locale": "en-GB", "Description": "Phoebe EBIMIEKUMO"}], "ShortName": [{"Locale": "en-GB", "Description": "Phoebe EBIMIEKUMO"}], "Position": 1, "FieldStatus": 0, "LineupX": null, "LineupY": null}, {"IdPlayer": "498", "IdTeam": "1882893", "ShirtNumber": 5, "Status": 1, "SpecialStatus": null, "Captain": false, "PlayerName": [{"Locale": "en-GB", "Description": "Omo-Love BRANCH"}], "ShortName": [{"Locale": "en-GB", "Description": "Omo-Love BRANCH"}], "Position": 1, "FieldStatus": 0, "LineupX": null, "LineupY": null}, {"IdPlayer": "501", "IdTeam": "1882893", "ShirtNumber": 3, "Status": 1, "SpecialStatus": null, "Captain": false, "PlayerName": [{"Locale": "en-GB", "Description": "Ngozi EZEOCHA"}], "ShortName": [{"Locale": "en-GB", "Description": "Ngozi EZEOCHA"}], "Position": 1, "FieldStatus": 0, "LineupX": null, "LineupY": null}, {"IdPlayer": "196", "IdTeam": "1882893", "ShirtNumber": 13, "Status": 1, "SpecialStatus": null, "Captain": false, "PlayerName": [{"Locale": "en-GB", "Description": "Nkiru OKOSIEME"}], "ShortName": [{"Locale": "en-GB", "Description": "OKOSIEME"}], "Position": 2, "FieldStatus": 0, "LineupX": null, "LineupY": null}, {"IdPlayer": "505", "IdTeam": "1882893", "ShirtNumber": 20, "Status": 1, "SpecialStatus": null, "Captain": false, "PlayerName": [{"Locale": "en-GB", "Description": "Ann MUKORO"}], "ShortName": [{"Locale": "en-GB", "Description": "Ann MUKORO"}], "Position": 2, "FieldStatus": 0, "LineupX": null, "LineupY": null}, {"IdPlayer": "183", "IdTeam": "1882893", "ShirtNumber": 12, "Status": 1, "SpecialStatus": null, "Captain": false, "PlayerName": [{"Locale": "en-GB", "Description": "Mercy AKIDE"}], "ShortName": [{"Locale": "en-GB", "Description": "AKIDE"}], "Position": 2, "FieldStatus": 0, "LineupX": null, "LineupY": null}, {"IdPlayer": "193", "IdTeam": "1882893", "ShirtNumber": 8, "Status": 1, "SpecialStatus": null, "Captain": false, "PlayerName": [{"Locale": "en-GB", "Description": "Rita NWADIKE"}], "ShortName": [{"Locale": "en-GB", "Description": "NWADIKE"}], "Position": 2, "FieldStatus": 0, "LineupX": null, "LineupY": null}, {"IdPlayer": "507", "IdTeam": "1882893", "ShirtNumber": 4, "Status": 1, "SpecialStatus": null, "Captain": false, "PlayerName": [{"Locale": "en-GB", "Description": "Adaku OKOROAFOR"}], "ShortName": [{"Locale": "en-GB", "Description": "Adaku OKOROAFOR"}], "Position": 3, "FieldStatus": 0, "LineupX": null, "LineupY": null}, {"IdPlayer": "197", "IdTeam": "1882893", "ShirtNumber": 2, "Status": 1, "SpecialStatus": null, "Captain": false, "PlayerName": [{"Locale": "en-GB", "Description": "Florence OMAGBEMI"}], "ShortName": [{"Locale": "en-GB", "Description": "OMAGBEMI"}], "Position": 1, "FieldStatus": 0, "LineupX": null, "LineupY": null}, {"IdPlayer": "188", "IdTeam": "1882893", "ShirtNumber": 11, "Status": 2, "SpecialStatus": null, "Captain": false, "PlayerName": [{"Locale": "en-GB", "Description": "Prisca EMEAFU"}], "ShortName": [{"Locale": "en-GB", "Description": "Prisca EMEAFU"}], "Position": 1, "FieldStatus": 0, "LineupX": null, "LineupY": null}, {"IdPlayer": "504", "IdTeam": "1882893", "ShirtNumber": 7, "Status": 2, "SpecialStatus": null, "Captain": false, "PlayerName": [{"Locale": "en-GB", "Description": "Nkechi MBILITAM"}], "ShortName": [{"Locale": "en-GB", "Description": "Nkechi MBILITAM"}], "Position": 2, "FieldStatus": 0, "LineupX": null, "LineupY": null}, {"IdPlayer": "190", "IdTeam": "1882893", "ShirtNumber": 6, "Status": 2, "SpecialStatus": null, "Captain": false, "PlayerName": [{"Locale": "en-GB", "Description": "Yinka KUDAISI"}], "ShortName": [{"Locale": "en-GB", "Description": "KUDAISI"}], "Position": 2, "FieldStatus": 0, "LineupX": null, "LineupY": null}, {"IdPlayer": "319382", "IdTeam": "1882893", "ShirtNumber": 9, "Status": 2, "SpecialStatus": null, "Captain": false, "PlayerName": [{"Locale": "en-GB", "Description": "Ngozi UCHE"}], "ShortName": [{"Locale": "en-GB", "Description": "Ngozi UCHE"}], "Position": 3, "FieldStatus": 0, "LineupX": null, "LineupY": null}, {"IdPlayer": "503", "IdTeam": "1882893", "ShirtNumber": 15, "Status": 2, "SpecialStatus": null, "Captain": false, "PlayerName": [{"Locale": "en-GB", "Description": "Maureen MMADU"}], "ShortName": [{"Locale": "en-GB", "Description": "MMADU"}], "Position": 3, "FieldStatus": 0, "LineupX": null, "LineupY": null}, {"IdPlayer": "181246", "IdTeam": "1882893", "ShirtNumber": 16, "Status": 2, "SpecialStatus": null, "Captain": false, "PlayerName": [{"Locale": "en-GB", "Description": "Ugochi OPARA"}], "ShortName": [{"Locale": "en-GB", "Description": "OPARA"}], "Position": 1, "FieldStatus": 0, "LineupX": null, "LineupY": null}, {"IdPlayer": "181247", "IdTeam": "1882893", "ShirtNumber": 17, "Status": 2, "SpecialStatus": null, "Captain": false, "PlayerName": [{"Locale": "en-GB", "Description": "Louisa AKPAGU"}], "ShortName": [{"Locale": "en-GB", "Description": "Louisa AKPAGU"}], "Position": 0, "FieldStatus": 0, "LineupX": null, "LineupY": null}, {"IdPlayer": "184", "IdTeam": "1882893", "ShirtNumber": 18, "Status": 2, "SpecialStatus": null, "Captain": false, "PlayerName": [{"Locale": "en-GB", "Description": "Patience AVRE"}], "ShortName": [{"Locale": "en-GB", "Description": "AVRE"}], "Position": 2, "FieldStatus": 0, "LineupX": null, "LineupY": null}, {"IdPlayer": "506", "IdTeam": "1882893", "ShirtNumber": 19, "Status": 2, "SpecialStatus": null, "Captain": false, "PlayerName": [{"Locale": "en-GB", "Description": "Diana NWAIWU"}], "ShortName": [{"Locale": "en-GB", "Description": "Diana NWAIWU"}], "Position": 0, "FieldStatus": 0, "LineupX": null, "LineupY": null}], "Bookings": [{"Card": 1, "Period": 5, "IdEvent": null, "EventNumber": null, "IdPlayer": "501", "IdTeam": "1882893", "Minute": "69", "Reason": null}, {"Card": 1, "Period": 5, "IdEvent": null, "EventNumber": null, "IdPlayer": "504", "IdTeam": "1882893", "Minute": "86", "Reason": null}], "Goals": [], "Substitutions": [{"IdEvent": null, "Period": 4, "Reason": 0, "SubstitutePosition": 2, "IdPlayerOff": "183", "IdPlayerOn": "184", "PlayerOffName": [{"Locale": "en-GB", "Description": "Mercy AKIDE"}], "PlayerOnName": [{"Locale": "en-GB", "Description": "Patience AVRE"}], "Minute": "45'", "IdTeam": "1882893"}, {"IdEvent": null, "Period": 5, "Reason": 0, "SubstitutePosition": 1, "IdPlayerOff": "501", "IdPlayerOn": "188", "PlayerOffName": [{"Locale": "en-GB", "Description": "Ngozi EZEOCHA"}], "PlayerOnName": [{"Locale": "en-GB", "Description": "Prisca EMEAFU"}], "Minute": "71'", "IdTeam": "1882893"}, {"IdEvent": null, "Period": 5, "Reason": 0, "SubstitutePosition": 1, "IdPlayerOff": "498", "IdPlayerOn": "504", "PlayerOffName": [{"Locale": "en-GB", "Description": "Omo-Love BRANCH"}], "PlayerOnName": [{"Locale": "en-GB", "Description": "Nkechi MBILITAM"}], "Minute": "73'", "IdTeam": "1882893"}], "FootballType": 0, "Gender": 2, "IdAssociation": "NGA"}, "BallPossession": {"Intervals": [], "LastX": [], "OverallHome": null, "OverallAway": null}, "TerritorialPossesion": null, "TerritorialThirdPossesion": null, "Officials": [{"IdCountry": "LUX", "OfficialId": "37270", "NameShort": [{"Locale": "en-GB", "Description": "Alain HAMER"}], "Name": [{"Locale": "en-GB", "Description": "HAMER Alain"}], "OfficialType": 1, "TypeLocalized": [{"Locale": "en-GB", "Description": "Referee"}]}, {"IdCountry": "JPN", "OfficialId": "41471", "NameShort": [{"Locale": "en-GB", "Description": "Hisae YOSHIZAWA"}], "Name": [{"Locale": "en-GB", "Description": "YOSHIZAWA Hisae"}], "OfficialType": 2, "TypeLocalized": [{"Locale": "en-GB", "Description": "Assistant Referee 1"}]}, {"IdCountry": "DEN", "OfficialId": "40514", "NameShort": [{"Locale": "en-GB", "Description": "Gitte HOLM"}], "Name": [{"Locale": "en-GB", "Description": "HOLM Gitte"}], "OfficialType": 3, "TypeLocalized": [{"Locale": "en-GB", "Description": "Assistant Referee 2"}]}], "MatchStatus": 0, "GroupName": [{"Locale": "en-GB", "Description": "Group B"}], "StageName": [{"Locale": "en-GB", "Description": "Group Matches"}], "OfficialityStatus": 0, "TimeDefined": true, "Properties": {}, "IsUpdateable": null}