{"IdMatch": "300269479", "IdStage": "268020", "IdGroup": "268030", "IdSeason": "266030", "IdCompetition": "103", "CompetitionName": [{"Locale": "en-GB", "Description": "FIFA Women's World Cup\u2122"}], "SeasonName": [{"Locale": "en-GB", "Description": "FIFA Women's World Cup Canada 2015"}], "SeasonShortName": [{"Locale": "en-GB", "Description": "Canada 2015"}], "Stadium": {"IdStadium": "5026358", "Name": [{"Locale": "en-GB", "Description": "Moncton Stadium"}], "Capacity": null, "WebAddress": null, "Built": null, "Roof": false, "Turf": null, "IdCity": "1000000209", "CityName": [{"Locale": "en-GB", "Description": "Moncton"}], "IdCountry": "CAN", "PostalCode": null, "Street": null, "Email": null, "Fax": null, "Phone": null, "AffiliationCountry": null, "AffiliationRegion": null, "Latitude": null, "Longitude": null, "Length": null, "Width": null, "Properties": {"IdIFES": "5026358"}, "IsUpdateable": null}, "ResultType": 0, "MatchDay": null, "HomeTeamPenaltyScore": null, "AwayTeamPenaltyScore": null, "AggregateHomeTeamScore": null, "AggregateAwayTeamScore": null, "Weather": null, "Attendance": null, "Date": "2015-06-13T17:00:00Z", "LocalDate": "2015-06-13T14:00:00Z", "MatchTime": null, "SecondHalfTime": null, "FirstHalfTime": null, "FirstHalfExtraTime": null, "SecondHalfExtraTime": null, "Winner": "1885035", "Period": 10, "HomeTeam": {"Score": 0, "Side": null, "IdTeam": "1884761", "PictureUrl": "https://api.fifa.com/api/v1/picture/flags-{format}-{size}/FRA", "IdCountry": "FRA", "TeamType": 1, "AgeType": 7, "Tactics": null, "TeamName": [{"Locale": "en-GB", "Description": "France"}], "Abbreviation": "FRA", "Coaches": [{"IdCoach": "69342", "IdCountry": "FRA", "Name": [{"Locale": "en-GB", "Description": "BERGEROO Philippe"}], "Alias": [{"Locale": "en-GB", "Description": "Philippe BERGEROO"}], "Role": 0}], "Players": [{"IdPlayer": "191348", "IdTeam": "1884761", "ShirtNumber": 1, "Status": 2, "SpecialStatus": null, "Captain": false, "PlayerName": [{"Locale": "en-GB", "Description": "Celine DEVILLE"}], "ShortName": [{"Locale": "en-GB", "Description": "DEVILLE"}], "Position": 0, "FieldStatus": 0, "LineupX": null, "LineupY": null}, {"IdPlayer": "302715", "IdTeam": "1884761", "ShirtNumber": 2, "Status": 1, "SpecialStatus": null, "Captain": true, "PlayerName": [{"Locale": "en-GB", "Description": "Wendie RENARD"}], "ShortName": [{"Locale": "en-GB", "Description": "RENARD"}], "Position": 1, "FieldStatus": 0, "LineupX": null, "LineupY": null}, {"IdPlayer": "237681", "IdTeam": "1884761", "ShirtNumber": 3, "Status": 1, "SpecialStatus": null, "Captain": false, "PlayerName": [{"Locale": "en-GB", "Description": "Laure BOULLEAU"}], "ShortName": [{"Locale": "en-GB", "Description": "BOULLEAU"}], "Position": 1, "FieldStatus": 0, "LineupX": null, "LineupY": null}, {"IdPlayer": "190244", "IdTeam": "1884761", "ShirtNumber": 4, "Status": 1, "SpecialStatus": null, "Captain": false, "PlayerName": [{"Locale": "en-GB", "Description": "Laura GEORGES"}], "ShortName": [{"Locale": "en-GB", "Description": "GEORGES"}], "Position": 1, "FieldStatus": 0, "LineupX": null, "LineupY": null}, {"IdPlayer": "237680", "IdTeam": "1884761", "ShirtNumber": 5, "Status": 2, "SpecialStatus": null, "Captain": false, "PlayerName": [{"Locale": "en-GB", "Description": "Sabrina DELANNOY"}], "ShortName": [{"Locale": "en-GB", "Description": "Delannoy"}], "Position": 1, "FieldStatus": 0, "LineupX": null, "LineupY": null}, {"IdPlayer": "254965", "IdTeam": "1884761", "ShirtNumber": 6, "Status": 2, "SpecialStatus": null, "Captain": false, "PlayerName": [{"Locale": "en-GB", "Description": "Amandine HENRY"}], "ShortName": [{"Locale": "en-GB", "Description": "HENRY"}], "Position": 2, "FieldStatus": 0, "LineupX": null, "LineupY": null}, {"IdPlayer": "301151", "IdTeam": "1884761", "ShirtNumber": 7, "Status": 1, "SpecialStatus": null, "Captain": false, "PlayerName": [{"Locale": "en-GB", "Description": "Kenza DALI"}], "ShortName": [{"Locale": "en-GB", "Description": "DALI"}], "Position": 2, "FieldStatus": 0, "LineupX": null, "LineupY": null}, {"IdPlayer": "237686", "IdTeam": "1884761", "ShirtNumber": 8, "Status": 1, "SpecialStatus": null, "Captain": false, "PlayerName": [{"Locale": "en-GB", "Description": "Jessica HOUARA"}], "ShortName": [{"Locale": "en-GB", "Description": "HOUARA D'H"}], "Position": 1, "FieldStatus": 0, "LineupX": null, "LineupY": null}, {"IdPlayer": "254849", "IdTeam": "1884761", "ShirtNumber": 9, "Status": 1, "SpecialStatus": null, "Captain": false, "PlayerName": [{"Locale": "en-GB", "Description": "Eugenie LE SOMMER"}], "ShortName": [{"Locale": "en-GB", "Description": "LE SOMMER"}], "Position": 3, "FieldStatus": 0, "LineupX": null, "LineupY": null}, {"IdPlayer": "190233", "IdTeam": "1884761", "ShirtNumber": 10, "Status": 1, "SpecialStatus": null, "Captain": false, "PlayerName": [{"Locale": "en-GB", "Description": "Camille ABILY"}], "ShortName": [{"Locale": "en-GB", "Description": "ABILY"}], "Position": 2, "FieldStatus": 0, "LineupX": null, "LineupY": null}, {"IdPlayer": "381298", "IdTeam": "1884761", "ShirtNumber": 11, "Status": 2, "SpecialStatus": null, "Captain": false, "PlayerName": [{"Locale": "en-GB", "Description": "Claire LAVOGEZ"}], "ShortName": [{"Locale": "en-GB", "Description": "LAVOGEZ"}], "Position": 2, "FieldStatus": 0, "LineupX": null, "LineupY": null}, {"IdPlayer": "237692", "IdTeam": "1884761", "ShirtNumber": 12, "Status": 2, "SpecialStatus": null, "Captain": false, "PlayerName": [{"Locale": "en-GB", "Description": "Elodie THOMIS"}], "ShortName": [{"Locale": "en-GB", "Description": "THOMIS"}], "Position": 2, "FieldStatus": 0, "LineupX": null, "LineupY": null}, {"IdPlayer": "358573", "IdTeam": "1884761", "ShirtNumber": 13, "Status": 2, "SpecialStatus": null, "Captain": false, "PlayerName": [{"Locale": "en-GB", "Description": "Kadidiatou DIANI"}], "ShortName": [{"Locale": "en-GB", "Description": "DIANI"}], "Position": 3, "FieldStatus": 0, "LineupX": null, "LineupY": null}, {"IdPlayer": "237688", "IdTeam": "1884761", "ShirtNumber": 14, "Status": 1, "SpecialStatus": null, "Captain": false, "PlayerName": [{"Locale": "en-GB", "Description": "Louisa NECIB"}], "ShortName": [{"Locale": "en-GB", "Description": "CADAMURO"}], "Position": 2, "FieldStatus": 0, "LineupX": null, "LineupY": null}, {"IdPlayer": "190239", "IdTeam": "1884761", "ShirtNumber": 15, "Status": 1, "SpecialStatus": null, "Captain": false, "PlayerName": [{"Locale": "en-GB", "Description": "Elise BUSSAGLIA"}], "ShortName": [{"Locale": "en-GB", "Description": "BUSSAGLIA"}], "Position": 2, "FieldStatus": 0, "LineupX": null, "LineupY": null}, {"IdPlayer": "190236", "IdTeam": "1884761", "ShirtNumber": 16, "Status": 1, "SpecialStatus": null, "Captain": false, "PlayerName": [{"Locale": "en-GB", "Description": "Sarah BOUHADDI"}], "ShortName": [{"Locale": "en-GB", "Description": "BOUHADDI"}], "Position": 0, "FieldStatus": 0, "LineupX": null, "LineupY": null}, {"IdPlayer": "328149", "IdTeam": "1884761", "ShirtNumber": 17, "Status": 1, "SpecialStatus": null, "Captain": false, "PlayerName": [{"Locale": "en-GB", "Description": "Gaetane THINEY"}], "ShortName": [{"Locale": "en-GB", "Description": "THINEY"}], "Position": 3, "FieldStatus": 0, "LineupX": null, "LineupY": null}, {"IdPlayer": "237695", "IdTeam": "1884761", "ShirtNumber": 18, "Status": 2, "SpecialStatus": null, "Captain": false, "PlayerName": [{"Locale": "en-GB", "Description": "Marie Laure DELIE"}], "ShortName": [{"Locale": "en-GB", "Description": "Delie"}], "Position": 3, "FieldStatus": 0, "LineupX": null, "LineupY": null}, {"IdPlayer": "358667", "IdTeam": "1884761", "ShirtNumber": 19, "Status": 2, "SpecialStatus": null, "Captain": false, "PlayerName": [{"Locale": "en-GB", "Description": "Griedge MBOCK BATHY"}], "ShortName": [{"Locale": "en-GB", "Description": "MBOCK BATHY"}], "Position": 1, "FieldStatus": 0, "LineupX": null, "LineupY": null}, {"IdPlayer": "300658", "IdTeam": "1884761", "ShirtNumber": 20, "Status": 2, "SpecialStatus": null, "Captain": false, "PlayerName": [{"Locale": "en-GB", "Description": "Annaig BUTEL"}], "ShortName": [{"Locale": "en-GB", "Description": "BUTEL"}], "Position": 1, "FieldStatus": 0, "LineupX": null, "LineupY": null}, {"IdPlayer": "302298", "IdTeam": "1884761", "ShirtNumber": 21, "Status": 2, "SpecialStatus": null, "Captain": false, "PlayerName": [{"Locale": "en-GB", "Description": "Meline GERARD"}], "ShortName": [{"Locale": "en-GB", "Description": "Meline GERARD"}], "Position": 0, "FieldStatus": 0, "LineupX": null, "LineupY": null}, {"IdPlayer": "387218", "IdTeam": "1884761", "ShirtNumber": 22, "Status": 2, "SpecialStatus": null, "Captain": false, "PlayerName": [{"Locale": "en-GB", "Description": "Amel MAJRI"}], "ShortName": [{"Locale": "en-GB", "Description": "MAJRI"}], "Position": 1, "FieldStatus": 0, "LineupX": null, "LineupY": null}, {"IdPlayer": "302750", "IdTeam": "1884761", "ShirtNumber": 23, "Status": 2, "SpecialStatus": null, "Captain": false, "PlayerName": [{"Locale": "en-GB", "Description": "Kheira HAMRAOUI"}], "ShortName": [{"Locale": "en-GB", "Description": "Hamraoui"}], "Position": 2, "FieldStatus": 0, "LineupX": null, "LineupY": null}], "Bookings": [], "Goals": [], "Substitutions": [{"IdEvent": null, "Period": 5, "Reason": 0, "SubstitutePosition": 2, "IdPlayerOff": "190239", "IdPlayerOn": "254965", "PlayerOffName": [{"Locale": "en-GB", "Description": "Elise BUSSAGLIA"}], "PlayerOnName": [{"Locale": "en-GB", "Description": "Amandine HENRY"}], "Minute": "62'", "IdTeam": "1884761"}, {"IdEvent": null, "Period": 5, "Reason": 0, "SubstitutePosition": 2, "IdPlayerOff": "237688", "IdPlayerOn": "381298", "PlayerOffName": [{"Locale": "en-GB", "Description": "Louisa NECIB"}], "PlayerOnName": [{"Locale": "en-GB", "Description": "Claire LAVOGEZ"}], "Minute": "62'", "IdTeam": "1884761"}, {"IdEvent": null, "Period": 5, "Reason": 0, "SubstitutePosition": 2, "IdPlayerOff": "301151", "IdPlayerOn": "237695", "PlayerOffName": [{"Locale": "en-GB", "Description": "Kenza DALI"}], "PlayerOnName": [{"Locale": "en-GB", "Description": "Marie Laure DELIE"}], "Minute": "76'", "IdTeam": "1884761"}], "FootballType": 0, "Gender": 2, "IdAssociation": "FRA"}, "AwayTeam": {"Score": 2, "Side": null, "IdTeam": "1885035", "PictureUrl": "https://api.fifa.com/api/v1/picture/flags-{format}-{size}/COL", "IdCountry": "COL", "TeamType": 1, "AgeType": 7, "Tactics": null, "TeamName": [{"Locale": "en-GB", "Description": "Colombia"}], "Abbreviation": "COL", "Coaches": [{"IdCoach": "359103", "IdCountry": "COL", "Name": [{"Locale": "en-GB", "Description": "TABORDA Fabian"}], "Alias": [{"Locale": "en-GB", "Description": "Fabian TABORDA"}], "Role": 0}], "Players": [{"IdPlayer": "301286", "IdTeam": "1885035", "ShirtNumber": 1, "Status": 2, "SpecialStatus": null, "Captain": false, "PlayerName": [{"Locale": "en-GB", "Description": "Stefany CASTANO"}], "ShortName": [{"Locale": "en-GB", "Description": "CASTA\u00d1O"}], "Position": 0, "FieldStatus": 0, "LineupX": null, "LineupY": null}, {"IdPlayer": "358924", "IdTeam": "1885035", "ShirtNumber": 2, "Status": 2, "SpecialStatus": null, "Captain": false, "PlayerName": [{"Locale": "en-GB", "Description": "Carolina ARBELAEZ"}], "ShortName": [{"Locale": "en-GB", "Description": "Arbelaez"}], "Position": 2, "FieldStatus": 0, "LineupX": null, "LineupY": null}, {"IdPlayer": "266400", "IdTeam": "1885035", "ShirtNumber": 3, "Status": 1, "SpecialStatus": null, "Captain": true, "PlayerName": [{"Locale": "en-GB", "Description": "Natalia GAITAN"}], "ShortName": [{"Locale": "en-GB", "Description": "GAITAN"}], "Position": 1, "FieldStatus": 0, "LineupX": null, "LineupY": null}, {"IdPlayer": "266402", "IdTeam": "1885035", "ShirtNumber": 4, "Status": 1, "SpecialStatus": null, "Captain": false, "PlayerName": [{"Locale": "en-GB", "Description": "Diana OSPINA"}], "ShortName": [{"Locale": "en-GB", "Description": "OSPINA"}], "Position": 2, "FieldStatus": 0, "LineupX": null, "LineupY": null}, {"IdPlayer": "387186", "IdTeam": "1885035", "ShirtNumber": 5, "Status": 2, "SpecialStatus": null, "Captain": false, "PlayerName": [{"Locale": "en-GB", "Description": "Lina GRANADOS"}], "ShortName": [{"Locale": "en-GB", "Description": "L. GRANADOS"}], "Position": 1, "FieldStatus": 0, "LineupX": null, "LineupY": null}, {"IdPlayer": "324521", "IdTeam": "1885035", "ShirtNumber": 6, "Status": 1, "SpecialStatus": null, "Captain": false, "PlayerName": [{"Locale": "en-GB", "Description": "Daniela MONTOYA"}], "ShortName": [{"Locale": "en-GB", "Description": "D. MONTOYA"}], "Position": 2, "FieldStatus": 0, "LineupX": null, "LineupY": null}, {"IdPlayer": "296349", "IdTeam": "1885035", "ShirtNumber": 7, "Status": 1, "SpecialStatus": null, "Captain": false, "PlayerName": [{"Locale": "en-GB", "Description": "Ingrid VIDAL"}], "ShortName": [{"Locale": "en-GB", "Description": "VIDAL"}], "Position": 3, "FieldStatus": 0, "LineupX": null, "LineupY": null}, {"IdPlayer": "266406", "IdTeam": "1885035", "ShirtNumber": 8, "Status": 2, "SpecialStatus": null, "Captain": false, "PlayerName": [{"Locale": "en-GB", "Description": "Mildrey PINEDA"}], "ShortName": [{"Locale": "en-GB", "Description": "Mildrey PINEDA"}], "Position": 2, "FieldStatus": 0, "LineupX": null, "LineupY": null}, {"IdPlayer": "266409", "IdTeam": "1885035", "ShirtNumber": 9, "Status": 1, "SpecialStatus": null, "Captain": false, "PlayerName": [{"Locale": "en-GB", "Description": "Orianica VELASQUEZ"}], "ShortName": [{"Locale": "en-GB", "Description": "VELASQUEZ"}], "Position": 2, "FieldStatus": 0, "LineupX": null, "LineupY": null}, {"IdPlayer": "296354", "IdTeam": "1885035", "ShirtNumber": 10, "Status": 1, "SpecialStatus": null, "Captain": false, "PlayerName": [{"Locale": "en-GB", "Description": "Yorely RINCON"}], "ShortName": [{"Locale": "en-GB", "Description": "H. RINCON"}], "Position": 2, "FieldStatus": 0, "LineupX": null, "LineupY": null}, {"IdPlayer": "266411", "IdTeam": "1885035", "ShirtNumber": 11, "Status": 2, "SpecialStatus": null, "Captain": false, "PlayerName": [{"Locale": "en-GB", "Description": "Catalina USME"}], "ShortName": [{"Locale": "en-GB", "Description": "USME"}], "Position": 2, "FieldStatus": 0, "LineupX": null, "LineupY": null}, {"IdPlayer": "330075", "IdTeam": "1885035", "ShirtNumber": 12, "Status": 1, "SpecialStatus": null, "Captain": false, "PlayerName": [{"Locale": "en-GB", "Description": "Sandra SEPULVEDA"}], "ShortName": [{"Locale": "en-GB", "Description": "SEPULVEDA"}], "Position": 0, "FieldStatus": 0, "LineupX": null, "LineupY": null}, {"IdPlayer": "387181", "IdTeam": "1885035", "ShirtNumber": 13, "Status": 1, "SpecialStatus": null, "Captain": false, "PlayerName": [{"Locale": "en-GB", "Description": "Angela CLAVIJO"}], "ShortName": [{"Locale": "en-GB", "Description": "CLAVIJO"}], "Position": 1, "FieldStatus": 0, "LineupX": null, "LineupY": null}, {"IdPlayer": "330076", "IdTeam": "1885035", "ShirtNumber": 14, "Status": 1, "SpecialStatus": null, "Captain": false, "PlayerName": [{"Locale": "en-GB", "Description": "Nataly ARIAS"}], "ShortName": [{"Locale": "en-GB", "Description": "ARIAS N."}], "Position": 1, "FieldStatus": 0, "LineupX": null, "LineupY": null}, {"IdPlayer": "296359", "IdTeam": "1885035", "ShirtNumber": 15, "Status": 2, "SpecialStatus": null, "Captain": false, "PlayerName": [{"Locale": "en-GB", "Description": "Tatiana ARIZA"}], "ShortName": [{"Locale": "en-GB", "Description": "ARIZA"}], "Position": 3, "FieldStatus": 0, "LineupX": null, "LineupY": null}, {"IdPlayer": "296357", "IdTeam": "1885035", "ShirtNumber": 16, "Status": 1, "SpecialStatus": null, "Captain": false, "PlayerName": [{"Locale": "en-GB", "Description": "Lady ANDRADE"}], "ShortName": [{"Locale": "en-GB", "Description": "ANDRADE"}], "Position": 3, "FieldStatus": 0, "LineupX": null, "LineupY": null}, {"IdPlayer": "322716", "IdTeam": "1885035", "ShirtNumber": 17, "Status": 1, "SpecialStatus": null, "Captain": false, "PlayerName": [{"Locale": "en-GB", "Description": "Carolina ARIAS"}], "ShortName": [{"Locale": "en-GB", "Description": "ARIAS C."}], "Position": 1, "FieldStatus": 0, "LineupX": null, "LineupY": null}, {"IdPlayer": "387183", "IdTeam": "1885035", "ShirtNumber": 18, "Status": 2, "SpecialStatus": null, "Captain": false, "PlayerName": [{"Locale": "en-GB", "Description": "Yisela CUESTA"}], "ShortName": [{"Locale": "en-GB", "Description": "CUESTA"}], "Position": 3, "FieldStatus": 0, "LineupX": null, "LineupY": null}, {"IdPlayer": "358920", "IdTeam": "1885035", "ShirtNumber": 19, "Status": 2, "SpecialStatus": null, "Captain": false, "PlayerName": [{"Locale": "en-GB", "Description": "Leicy SANTOS"}], "ShortName": [{"Locale": "en-GB", "Description": "SANTOS"}], "Position": 2, "FieldStatus": 0, "LineupX": null, "LineupY": null}, {"IdPlayer": "296353", "IdTeam": "1885035", "ShirtNumber": 20, "Status": 2, "SpecialStatus": null, "Captain": false, "PlayerName": [{"Locale": "en-GB", "Description": "Laura COSME"}], "ShortName": [{"Locale": "en-GB", "Description": "COSME"}], "Position": 3, "FieldStatus": 0, "LineupX": null, "LineupY": null}, {"IdPlayer": "387182", "IdTeam": "1885035", "ShirtNumber": 21, "Status": 2, "SpecialStatus": null, "Captain": false, "PlayerName": [{"Locale": "en-GB", "Description": "Isabella ECHEVERRI"}], "ShortName": [{"Locale": "en-GB", "Description": "ECHEVERRI"}], "Position": 2, "FieldStatus": 0, "LineupX": null, "LineupY": null}, {"IdPlayer": "324728", "IdTeam": "1885035", "ShirtNumber": 22, "Status": 2, "SpecialStatus": null, "Captain": false, "PlayerName": [{"Locale": "en-GB", "Description": "Catalina PEREZ"}], "ShortName": [{"Locale": "en-GB", "Description": "P\u00e9rez"}], "Position": 0, "FieldStatus": 0, "LineupX": null, "LineupY": null}, {"IdPlayer": "387184", "IdTeam": "1885035", "ShirtNumber": 23, "Status": 2, "SpecialStatus": null, "Captain": false, "PlayerName": [{"Locale": "en-GB", "Description": "Manuela GONZALEZ"}], "ShortName": [{"Locale": "en-GB", "Description": "M. GONZALEZ"}], "Position": 3, "FieldStatus": 0, "LineupX": null, "LineupY": null}], "Bookings": [{"Card": 1, "Period": 5, "IdEvent": null, "EventNumber": null, "IdPlayer": "330075", "IdTeam": "1885035", "Minute": "68", "Reason": null}, {"Card": 1, "Period": 5, "IdEvent": null, "EventNumber": null, "IdPlayer": "266402", "IdTeam": "1885035", "Minute": "78", "Reason": null}], "Goals": [{"Type": 2, "IdPlayer": "296357", "Minute": "18'", "IdAssistPlayer": null, "Period": 3, "IdGoal": null, "IdTeam": "1885035"}, {"Type": 2, "IdPlayer": "266411", "Minute": "90'+2'", "IdAssistPlayer": null, "Period": 5, "IdGoal": null, "IdTeam": "1885035"}], "Substitutions": [{"IdEvent": null, "Period": 5, "Reason": 0, "SubstitutePosition": 3, "IdPlayerOff": "296349", "IdPlayerOn": "266411", "PlayerOffName": [{"Locale": "en-GB", "Description": "Ingrid VIDAL"}], "PlayerOnName": [{"Locale": "en-GB", "Description": "Catalina USME"}], "Minute": "54'", "IdTeam": "1885035"}, {"IdEvent": null, "Period": 5, "Reason": 0, "SubstitutePosition": 2, "IdPlayerOff": "296354", "IdPlayerOn": "387182", "PlayerOffName": [{"Locale": "en-GB", "Description": "Yorely RINCON"}], "PlayerOnName": [{"Locale": "en-GB", "Description": "Isabella ECHEVERRI"}], "Minute": "86'", "IdTeam": "1885035"}, {"IdEvent": null, "Period": 5, "Reason": 0, "SubstitutePosition": 3, "IdPlayerOff": "296357", "IdPlayerOn": "296359", "PlayerOffName": [{"Locale": "en-GB", "Description": "Lady ANDRADE"}], "PlayerOnName": [{"Locale": "en-GB", "Description": "Tatiana ARIZA"}], "Minute": "90'", "IdTeam": "1885035"}], "FootballType": 0, "Gender": 2, "IdAssociation": "COL"}, "BallPossession": {"Intervals": [], "LastX": [], "OverallHome": null, "OverallAway": null}, "TerritorialPossesion": null, "TerritorialThirdPossesion": null, "Officials": [{"IdCountry": "CHN", "OfficialId": "281456", "NameShort": [{"Locale": "en-GB", "Description": "QIN Liang"}], "Name": [{"Locale": "en-GB", "Description": "QIN Liang"}], "OfficialType": 1, "TypeLocalized": [{"Locale": "en-GB", "Description": "Main referee"}]}, {"IdCountry": "CHN", "OfficialId": "281460", "NameShort": [{"Locale": "en-GB", "Description": "CUI Yongmei"}], "Name": [{"Locale": "en-GB", "Description": "CUI Yongmei"}], "OfficialType": 2, "TypeLocalized": [{"Locale": "en-GB", "Description": "Lineman 1"}]}, {"IdCountry": "CHN", "OfficialId": "315813", "NameShort": [{"Locale": "en-GB", "Description": "FANG Yan"}], "Name": [{"Locale": "en-GB", "Description": "FANG Yan"}], "OfficialType": 3, "TypeLocalized": [{"Locale": "en-GB", "Description": "Lineman 2"}]}, {"IdCountry": "CAN", "OfficialId": "257476", "NameShort": [{"Locale": "en-GB", "Description": "Michelle PYE"}], "Name": [{"Locale": "en-GB", "Description": "PYE Michelle"}], "OfficialType": 4, "TypeLocalized": [{"Locale": "en-GB", "Description": "Fourth official"}]}, {"IdCountry": "ARG", "OfficialId": "282627", "NameShort": [{"Locale": "en-GB", "Description": "Maria ROCCO"}], "Name": [{"Locale": "en-GB", "Description": "ROCCO Maria"}], "OfficialType": 6, "TypeLocalized": [{"Locale": "en-GB", "Description": "Reserve referee"}]}], "MatchStatus": 0, "GroupName": [{"Locale": "en-GB", "Description": "Group F"}], "StageName": [{"Locale": "en-GB", "Description": "First Stage"}], "OfficialityStatus": 0, "TimeDefined": true, "Properties": {}, "IsUpdateable": null}