{"IdMatch": "300438225", "IdStage": "278527", "IdGroup": "278531", "IdSeason": "278513", "IdCompetition": "103", "CompetitionName": [{"Locale": "en-GB", "Description": "FIFA Women's World Cup\u2122"}], "SeasonName": [{"Locale": "en-GB", "Description": "FIFA Women's World Cup France 2019\u2122"}], "SeasonShortName": [], "Stadium": {"IdStadium": "4", "Name": [{"Locale": "en-GB", "Description": "Stade de la Mosson"}], "Capacity": null, "WebAddress": null, "Built": null, "Roof": false, "Turf": null, "IdCity": "17882", "CityName": [{"Locale": "en-GB", "Description": "Montpellier"}], "IdCountry": "FRA", "PostalCode": null, "Street": null, "Email": null, "Fax": null, "Phone": null, "AffiliationCountry": null, "AffiliationRegion": null, "Latitude": null, "Longitude": null, "Length": null, "Width": null, "Properties": {"IdIFES": "4"}, "IsUpdateable": null}, "ResultType": 1, "MatchDay": "7", "HomeTeamPenaltyScore": 0, "AwayTeamPenaltyScore": 0, "AggregateHomeTeamScore": 0, "AggregateAwayTeamScore": 0, "Weather": {"Humidity": "45", "Temperature": "22", "WindSpeed": "23", "Type": 4, "TypeLocalized": [{"Locale": "en-GB", "Description": "Partly Cloudy"}]}, "Attendance": "17032", "Date": "2019-06-13T16:00:00Z", "LocalDate": "2019-06-13T18:00:00Z", "MatchTime": "0'", "SecondHalfTime": null, "FirstHalfTime": null, "FirstHalfExtraTime": null, "SecondHalfExtraTime": null, "Winner": "1882891", "Period": 10, "HomeTeam": {"Score": 3, "Side": null, "IdTeam": "1882891", "PictureUrl": "https://api.fifa.com/api/v1/picture/flags-{format}-{size}/AUS", "IdCountry": "AUS", "TeamType": 1, "AgeType": 7, "Tactics": "4-3-3", "TeamName": [{"Locale": "en-GB", "Description": "Australia"}], "Abbreviation": "AUS", "Coaches": [{"IdCoach": "193508", "IdCountry": "AUS", "Name": [{"Locale": "en-GB", "Description": "Ante MILICIC"}], "Alias": [{"Locale": "en-GB", "Description": "Ante MILICIC"}], "Role": 0}], "Players": [{"IdPlayer": "225531", "IdTeam": "1882891", "ShirtNumber": 1, "Status": 1, "SpecialStatus": 2, "Captain": false, "PlayerName": [{"Locale": "en-GB", "Description": "Lydia WILLIAMS"}], "ShortName": [{"Locale": "en-GB", "Description": "WILLIAMS"}], "Position": 0, "FieldStatus": 1, "LineupX": -0.895238, "LineupY": 0.002941}, {"IdPlayer": "394094", "IdTeam": "1882891", "ShirtNumber": 6, "Status": 1, "SpecialStatus": 2, "Captain": false, "PlayerName": [{"Locale": "en-GB", "Description": "Chloe LOGARZO"}], "ShortName": [{"Locale": "en-GB", "Description": "LOGARZO"}], "Position": 2, "FieldStatus": 1, "LineupX": 0.057143, "LineupY": 0.485294}, {"IdPlayer": "386998", "IdTeam": "1882891", "ShirtNumber": 7, "Status": 1, "SpecialStatus": 2, "Captain": false, "PlayerName": [{"Locale": "en-GB", "Description": "Steph CATLEY"}], "ShortName": [{"Locale": "en-GB", "Description": "CATLEY"}], "Position": 1, "FieldStatus": 1, "LineupX": -0.504762, "LineupY": 0.242647}, {"IdPlayer": "255278", "IdTeam": "1882891", "ShirtNumber": 8, "Status": 1, "SpecialStatus": 2, "Captain": false, "PlayerName": [{"Locale": "en-GB", "Description": "Elise KELLOND-KNIGHT"}], "ShortName": [{"Locale": "en-GB", "Description": "KELLOND-KNIGHT"}], "Position": 2, "FieldStatus": 1, "LineupX": -0.390476, "LineupY": 0.573529}, {"IdPlayer": "326979", "IdTeam": "1882891", "ShirtNumber": 9, "Status": 1, "SpecialStatus": 2, "Captain": false, "PlayerName": [{"Locale": "en-GB", "Description": "Caitlin FOORD"}], "ShortName": [{"Locale": "en-GB", "Description": "FOORD"}], "Position": 3, "FieldStatus": 2, "LineupX": 0.552381, "LineupY": 0.485294}, {"IdPlayer": "326968", "IdTeam": "1882891", "ShirtNumber": 10, "Status": 1, "SpecialStatus": 2, "Captain": false, "PlayerName": [{"Locale": "en-GB", "Description": "Emily VAN EGMOND"}], "ShortName": [{"Locale": "en-GB", "Description": "VAN EGMOND"}], "Position": 2, "FieldStatus": 1, "LineupX": 0.057143, "LineupY": 0.002941}, {"IdPlayer": "326972", "IdTeam": "1882891", "ShirtNumber": 13, "Status": 1, "SpecialStatus": 2, "Captain": false, "PlayerName": [{"Locale": "en-GB", "Description": "Tameka YALLOP"}], "ShortName": [{"Locale": "en-GB", "Description": "YALLOP"}], "Position": 2, "FieldStatus": 1, "LineupX": 0.057143, "LineupY": -0.485294}, {"IdPlayer": "386994", "IdTeam": "1882891", "ShirtNumber": 14, "Status": 1, "SpecialStatus": 2, "Captain": false, "PlayerName": [{"Locale": "en-GB", "Description": "Alanna KENNEDY"}], "ShortName": [{"Locale": "en-GB", "Description": "KENNEDY"}], "Position": 1, "FieldStatus": 1, "LineupX": -0.504762, "LineupY": -0.242647}, {"IdPlayer": "395166", "IdTeam": "1882891", "ShirtNumber": 15, "Status": 1, "SpecialStatus": 2, "Captain": false, "PlayerName": [{"Locale": "en-GB", "Description": "Emily GIELNIK"}], "ShortName": [{"Locale": "en-GB", "Description": "GIELNIK"}], "Position": 3, "FieldStatus": 2, "LineupX": 0.552381, "LineupY": -0.485294}, {"IdPlayer": "326971", "IdTeam": "1882891", "ShirtNumber": 20, "Status": 1, "SpecialStatus": 3, "Captain": true, "PlayerName": [{"Locale": "en-GB", "Description": "Sam KERR"}], "ShortName": [{"Locale": "en-GB", "Description": "KERR"}], "Position": 3, "FieldStatus": 1, "LineupX": 0.552381, "LineupY": 0.002941}, {"IdPlayer": "394063", "IdTeam": "1882891", "ShirtNumber": 21, "Status": 1, "SpecialStatus": 2, "Captain": false, "PlayerName": [{"Locale": "en-GB", "Description": "Ellie CARPENTER"}], "ShortName": [{"Locale": "en-GB", "Description": "CARPENTER"}], "Position": 1, "FieldStatus": 1, "LineupX": -0.390476, "LineupY": -0.573529}, {"IdPlayer": "332984", "IdTeam": "1882891", "ShirtNumber": 2, "Status": 2, "SpecialStatus": null, "Captain": false, "PlayerName": [{"Locale": "en-GB", "Description": "Gema SIMON"}], "ShortName": [{"Locale": "en-GB", "Description": "SIMON"}], "Position": 1, "FieldStatus": 2, "LineupX": null, "LineupY": null}, {"IdPlayer": "326967", "IdTeam": "1882891", "ShirtNumber": 3, "Status": 2, "SpecialStatus": null, "Captain": false, "PlayerName": [{"Locale": "en-GB", "Description": "Aivi LUIK"}], "ShortName": [{"Locale": "en-GB", "Description": "LUIK"}], "Position": 2, "FieldStatus": 2, "LineupX": null, "LineupY": null}, {"IdPlayer": "419882", "IdTeam": "1882891", "ShirtNumber": 5, "Status": 2, "SpecialStatus": null, "Captain": false, "PlayerName": [{"Locale": "en-GB", "Description": "Karly ROESTBAKKEN"}], "ShortName": [{"Locale": "en-GB", "Description": "ROESTBAKKEN"}], "Position": 1, "FieldStatus": 1, "LineupX": null, "LineupY": null}, {"IdPlayer": "190165", "IdTeam": "1882891", "ShirtNumber": 11, "Status": 2, "SpecialStatus": 4, "Captain": false, "PlayerName": [{"Locale": "en-GB", "Description": "Lisa DE VANNA"}], "ShortName": [{"Locale": "en-GB", "Description": "DE VANNA"}], "Position": 3, "FieldStatus": 2, "LineupX": null, "LineupY": null}, {"IdPlayer": "419880", "IdTeam": "1882891", "ShirtNumber": 12, "Status": 2, "SpecialStatus": null, "Captain": false, "PlayerName": [{"Locale": "en-GB", "Description": "Teagan MICAH"}], "ShortName": [{"Locale": "en-GB", "Description": "MICAH"}], "Position": 0, "FieldStatus": 2, "LineupX": null, "LineupY": null}, {"IdPlayer": "386995", "IdTeam": "1882891", "ShirtNumber": 16, "Status": 2, "SpecialStatus": null, "Captain": false, "PlayerName": [{"Locale": "en-GB", "Description": "Hayley RASO"}], "ShortName": [{"Locale": "en-GB", "Description": "RASO"}], "Position": 3, "FieldStatus": 1, "LineupX": null, "LineupY": null}, {"IdPlayer": "386993", "IdTeam": "1882891", "ShirtNumber": 18, "Status": 2, "SpecialStatus": null, "Captain": false, "PlayerName": [{"Locale": "en-GB", "Description": "Mackenzie ARNOLD"}], "ShortName": [{"Locale": "en-GB", "Description": "ARNOLD"}], "Position": 0, "FieldStatus": 2, "LineupX": null, "LineupY": null}, {"IdPlayer": "386996", "IdTeam": "1882891", "ShirtNumber": 19, "Status": 2, "SpecialStatus": null, "Captain": false, "PlayerName": [{"Locale": "en-GB", "Description": "Katrina GORRY"}], "ShortName": [{"Locale": "en-GB", "Description": "GORRY"}], "Position": 2, "FieldStatus": 2, "LineupX": null, "LineupY": null}, {"IdPlayer": "387001", "IdTeam": "1882891", "ShirtNumber": 22, "Status": 2, "SpecialStatus": null, "Captain": false, "PlayerName": [{"Locale": "en-GB", "Description": "Amy HARRISON"}], "ShortName": [{"Locale": "en-GB", "Description": "HARRISON"}], "Position": 2, "FieldStatus": 2, "LineupX": null, "LineupY": null}, {"IdPlayer": "326969", "IdTeam": "1882891", "ShirtNumber": 23, "Status": 2, "SpecialStatus": null, "Captain": false, "PlayerName": [{"Locale": "en-GB", "Description": "Teigen ALLEN"}], "ShortName": [{"Locale": "en-GB", "Description": "ALLEN"}], "Position": 1, "FieldStatus": 2, "LineupX": null, "LineupY": null}, {"IdPlayer": "251935", "IdTeam": "1882891", "ShirtNumber": 4, "Status": 2, "SpecialStatus": 8, "Captain": false, "PlayerName": [{"Locale": "en-GB", "Description": "Clare POLKINGHORNE"}], "ShortName": [{"Locale": "en-GB", "Description": "POLKINGHORNE"}], "Position": 1, "FieldStatus": 2, "LineupX": null, "LineupY": null}, {"IdPlayer": "419898", "IdTeam": "1882891", "ShirtNumber": 17, "Status": 2, "SpecialStatus": 8, "Captain": false, "PlayerName": [{"Locale": "en-GB", "Description": "Mary FOWLER"}], "ShortName": [{"Locale": "en-GB", "Description": "FOWLER"}], "Position": 3, "FieldStatus": 2, "LineupX": null, "LineupY": null}], "Bookings": [], "Goals": [{"Type": 2, "IdPlayer": "326979", "Minute": "45'+1'", "IdAssistPlayer": "251049", "Period": 3, "IdGoal": null, "IdTeam": "1882891"}, {"Type": 2, "IdPlayer": "394094", "Minute": "58'", "IdAssistPlayer": "251049", "Period": 5, "IdGoal": null, "IdTeam": "1882891"}, {"Type": 3, "IdPlayer": "251055", "Minute": "66'", "IdAssistPlayer": null, "Period": 5, "IdGoal": null, "IdTeam": "1882881"}], "Substitutions": [{"IdEvent": null, "Period": 5, "Reason": 0, "SubstitutePosition": 3, "IdPlayerOff": "395166", "IdPlayerOn": "386995", "PlayerOffName": [{"Locale": "en-GB", "Description": "Emily GIELNIK"}], "PlayerOnName": [{"Locale": "en-GB", "Description": "Hayley RASO"}], "Minute": "72'", "IdTeam": "1882891"}, {"IdEvent": null, "Period": 5, "Reason": 0, "SubstitutePosition": 1, "IdPlayerOff": "326979", "IdPlayerOn": "419882", "PlayerOffName": [{"Locale": "en-GB", "Description": "Caitlin FOORD"}], "PlayerOnName": [{"Locale": "en-GB", "Description": "Karly ROESTBAKKEN"}], "Minute": "90'+5'", "IdTeam": "1882891"}], "FootballType": 0, "Gender": 2, "IdAssociation": "AUS"}, "AwayTeam": {"Score": 2, "Side": null, "IdTeam": "1882881", "PictureUrl": "https://api.fifa.com/api/v1/picture/flags-{format}-{size}/BRA", "IdCountry": "BRA", "TeamType": 1, "AgeType": 7, "Tactics": "4-4-2", "TeamName": [{"Locale": "en-GB", "Description": "Brazil"}], "Abbreviation": "BRA", "Coaches": [{"IdCoach": "382834", "IdCountry": "BRA", "Name": [{"Locale": "en-GB", "Description": "VADAO"}], "Alias": [{"Locale": "en-GB", "Description": "VADAO"}], "Role": 0}], "Players": [{"IdPlayer": "251049", "IdTeam": "1882881", "ShirtNumber": 1, "Status": 1, "SpecialStatus": 2, "Captain": false, "PlayerName": [{"Locale": "en-GB", "Description": "BARBARA"}], "ShortName": [{"Locale": "en-GB", "Description": "BARBARA"}], "Position": 0, "FieldStatus": 1, "LineupX": -0.895238, "LineupY": 0.002941}, {"IdPlayer": "387316", "IdTeam": "1882881", "ShirtNumber": 5, "Status": 1, "SpecialStatus": 2, "Captain": false, "PlayerName": [{"Locale": "en-GB", "Description": "THAISA"}], "ShortName": [{"Locale": "en-GB", "Description": "THAISA"}], "Position": 2, "FieldStatus": 1, "LineupX": -0.057143, "LineupY": 0.301471}, {"IdPlayer": "215194", "IdTeam": "1882881", "ShirtNumber": 6, "Status": 1, "SpecialStatus": 2, "Captain": false, "PlayerName": [{"Locale": "en-GB", "Description": "TAMIRES"}], "ShortName": [{"Locale": "en-GB", "Description": "TAMIRES"}], "Position": 1, "FieldStatus": 1, "LineupX": -0.390476, "LineupY": 0.573529}, {"IdPlayer": "322662", "IdTeam": "1882881", "ShirtNumber": 7, "Status": 1, "SpecialStatus": 2, "Captain": false, "PlayerName": [{"Locale": "en-GB", "Description": "ANDRESSA"}], "ShortName": [{"Locale": "en-GB", "Description": "ANDRESSA"}], "Position": 2, "FieldStatus": 1, "LineupX": 0.152381, "LineupY": 0.573529}, {"IdPlayer": "31", "IdTeam": "1882881", "ShirtNumber": 8, "Status": 1, "SpecialStatus": 6, "Captain": false, "PlayerName": [{"Locale": "en-GB", "Description": "FORMIGA"}], "ShortName": [{"Locale": "en-GB", "Description": "FORMIGA"}], "Position": 2, "FieldStatus": 2, "LineupX": -0.057143, "LineupY": -0.301471}, {"IdPlayer": "322658", "IdTeam": "1882881", "ShirtNumber": 9, "Status": 1, "SpecialStatus": 2, "Captain": false, "PlayerName": [{"Locale": "en-GB", "Description": "DEBINHA"}], "ShortName": [{"Locale": "en-GB", "Description": "DEBINHA"}], "Position": 3, "FieldStatus": 1, "LineupX": 0.152381, "LineupY": -0.566176}, {"IdPlayer": "190358", "IdTeam": "1882881", "ShirtNumber": 10, "Status": 1, "SpecialStatus": 3, "Captain": true, "PlayerName": [{"Locale": "en-GB", "Description": "MARTA"}], "ShortName": [{"Locale": "en-GB", "Description": "MARTA"}], "Position": 3, "FieldStatus": 2, "LineupX": 0.552381, "LineupY": 0.345588}, {"IdPlayer": "190362", "IdTeam": "1882881", "ShirtNumber": 11, "Status": 1, "SpecialStatus": 2, "Captain": false, "PlayerName": [{"Locale": "en-GB", "Description": "CRISTIANE"}], "ShortName": [{"Locale": "en-GB", "Description": "CRISTIANE"}], "Position": 3, "FieldStatus": 2, "LineupX": 0.552381, "LineupY": -0.345588}, {"IdPlayer": "357729", "IdTeam": "1882881", "ShirtNumber": 13, "Status": 1, "SpecialStatus": 2, "Captain": false, "PlayerName": [{"Locale": "en-GB", "Description": "LETICIA SANTOS"}], "ShortName": [{"Locale": "en-GB", "Description": "L SANTOS"}], "Position": 1, "FieldStatus": 1, "LineupX": -0.390476, "LineupY": -0.566176}, {"IdPlayer": "420472", "IdTeam": "1882881", "ShirtNumber": 14, "Status": 1, "SpecialStatus": 2, "Captain": false, "PlayerName": [{"Locale": "en-GB", "Description": "KATHELLEN"}], "ShortName": [{"Locale": "en-GB", "Description": "KATHELLEN"}], "Position": 1, "FieldStatus": 1, "LineupX": -0.504762, "LineupY": -0.242647}, {"IdPlayer": "251055", "IdTeam": "1882881", "ShirtNumber": 21, "Status": 1, "SpecialStatus": 2, "Captain": false, "PlayerName": [{"Locale": "en-GB", "Description": "MONICA"}], "ShortName": [{"Locale": "en-GB", "Description": "M\u00d4NICA"}], "Position": 1, "FieldStatus": 1, "LineupX": -0.504762, "LineupY": 0.242647}, {"IdPlayer": "322664", "IdTeam": "1882881", "ShirtNumber": 2, "Status": 2, "SpecialStatus": null, "Captain": false, "PlayerName": [{"Locale": "en-GB", "Description": "POLIANA"}], "ShortName": [{"Locale": "en-GB", "Description": "POLIANA"}], "Position": 1, "FieldStatus": 2, "LineupX": null, "LineupY": null}, {"IdPlayer": "398373", "IdTeam": "1882881", "ShirtNumber": 3, "Status": 2, "SpecialStatus": 4, "Captain": false, "PlayerName": [{"Locale": "en-GB", "Description": "DAIANE"}], "ShortName": [{"Locale": "en-GB", "Description": "DAIANE"}], "Position": 1, "FieldStatus": 2, "LineupX": null, "LineupY": null}, {"IdPlayer": "357683", "IdTeam": "1882881", "ShirtNumber": 4, "Status": 2, "SpecialStatus": null, "Captain": false, "PlayerName": [{"Locale": "en-GB", "Description": "TAYLA"}], "ShortName": [{"Locale": "en-GB", "Description": "TAYLA"}], "Position": 1, "FieldStatus": 2, "LineupX": null, "LineupY": null}, {"IdPlayer": "395358", "IdTeam": "1882881", "ShirtNumber": 12, "Status": 2, "SpecialStatus": null, "Captain": false, "PlayerName": [{"Locale": "en-GB", "Description": "ALINE"}], "ShortName": [{"Locale": "en-GB", "Description": "ALINE REIS"}], "Position": 0, "FieldStatus": 2, "LineupX": null, "LineupY": null}, {"IdPlayer": "357768", "IdTeam": "1882881", "ShirtNumber": 15, "Status": 2, "SpecialStatus": null, "Captain": false, "PlayerName": [{"Locale": "en-GB", "Description": "CAMILA"}], "ShortName": [{"Locale": "en-GB", "Description": "CAMILA"}], "Position": 2, "FieldStatus": 2, "LineupX": null, "LineupY": null}, {"IdPlayer": "296328", "IdTeam": "1882881", "ShirtNumber": 16, "Status": 2, "SpecialStatus": null, "Captain": false, "PlayerName": [{"Locale": "en-GB", "Description": "BEATRIZ"}], "ShortName": [{"Locale": "en-GB", "Description": "BEATRIZ"}], "Position": 3, "FieldStatus": 1, "LineupX": null, "LineupY": null}, {"IdPlayer": "321158", "IdTeam": "1882881", "ShirtNumber": 17, "Status": 2, "SpecialStatus": null, "Captain": false, "PlayerName": [{"Locale": "en-GB", "Description": "ANDRESSINHA"}], "ShortName": [{"Locale": "en-GB", "Description": "ANDRESSINHA"}], "Position": 2, "FieldStatus": 2, "LineupX": null, "LineupY": null}, {"IdPlayer": "321165", "IdTeam": "1882881", "ShirtNumber": 18, "Status": 2, "SpecialStatus": null, "Captain": false, "PlayerName": [{"Locale": "en-GB", "Description": "LUANA"}], "ShortName": [{"Locale": "en-GB", "Description": "LUANA"}], "Position": 2, "FieldStatus": 1, "LineupX": null, "LineupY": null}, {"IdPlayer": "420479", "IdTeam": "1882881", "ShirtNumber": 19, "Status": 2, "SpecialStatus": null, "Captain": false, "PlayerName": [{"Locale": "en-GB", "Description": "LUDMILA"}], "ShortName": [{"Locale": "en-GB", "Description": "LUDMILA"}], "Position": 3, "FieldStatus": 1, "LineupX": null, "LineupY": null}, {"IdPlayer": "296327", "IdTeam": "1882881", "ShirtNumber": 20, "Status": 2, "SpecialStatus": null, "Captain": false, "PlayerName": [{"Locale": "en-GB", "Description": "RAQUEL FERNANDES"}], "ShortName": [{"Locale": "en-GB", "Description": "RAQUEL"}], "Position": 3, "FieldStatus": 2, "LineupX": null, "LineupY": null}, {"IdPlayer": "321160", "IdTeam": "1882881", "ShirtNumber": 22, "Status": 2, "SpecialStatus": null, "Captain": false, "PlayerName": [{"Locale": "en-GB", "Description": "LETICIA"}], "ShortName": [{"Locale": "en-GB", "Description": "LETICIA"}], "Position": 0, "FieldStatus": 2, "LineupX": null, "LineupY": null}, {"IdPlayer": "398377", "IdTeam": "1882881", "ShirtNumber": 23, "Status": 2, "SpecialStatus": null, "Captain": false, "PlayerName": [{"Locale": "en-GB", "Description": "GEYSE"}], "ShortName": [{"Locale": "en-GB", "Description": "GEYSE"}], "Position": 3, "FieldStatus": 2, "LineupX": null, "LineupY": null}], "Bookings": [{"Card": 1, "Period": 3, "IdEvent": null, "EventNumber": null, "IdPlayer": "31", "IdTeam": "1882881", "Minute": "14'", "Reason": null}, {"Card": 1, "Period": 5, "IdEvent": null, "EventNumber": null, "IdPlayer": "322662", "IdTeam": "1882881", "Minute": "85'", "Reason": null}, {"Card": 1, "Period": 5, "IdEvent": null, "EventNumber": null, "IdPlayer": "321165", "IdTeam": "1882881", "Minute": "87'", "Reason": null}], "Goals": [{"Type": 1, "IdPlayer": "190358", "Minute": "27'", "IdAssistPlayer": "225531", "Period": 3, "IdGoal": null, "IdTeam": "1882881"}, {"Type": 2, "IdPlayer": "190362", "Minute": "38'", "IdAssistPlayer": "225531", "Period": 3, "IdGoal": null, "IdTeam": "1882881"}], "Substitutions": [{"IdEvent": null, "Period": 4, "Reason": 0, "SubstitutePosition": 3, "IdPlayerOff": "190358", "IdPlayerOn": "420479", "PlayerOffName": [{"Locale": "en-GB", "Description": "MARTA"}], "PlayerOnName": [{"Locale": "en-GB", "Description": "LUDMILA"}], "Minute": "46'", "IdTeam": "1882881"}, {"IdEvent": null, "Period": 4, "Reason": 0, "SubstitutePosition": 2, "IdPlayerOff": "31", "IdPlayerOn": "321165", "PlayerOffName": [{"Locale": "en-GB", "Description": "FORMIGA"}], "PlayerOnName": [{"Locale": "en-GB", "Description": "LUANA"}], "Minute": "46'", "IdTeam": "1882881"}, {"IdEvent": null, "Period": 5, "Reason": 0, "SubstitutePosition": 3, "IdPlayerOff": "190362", "IdPlayerOn": "296328", "PlayerOffName": [{"Locale": "en-GB", "Description": "CRISTIANE"}], "PlayerOnName": [{"Locale": "en-GB", "Description": "BEATRIZ"}], "Minute": "75'", "IdTeam": "1882881"}], "FootballType": 0, "Gender": 2, "IdAssociation": "BRA"}, "BallPossession": {"Intervals": [], "LastX": [], "OverallHome": 51.0, "OverallAway": 49.0}, "TerritorialPossesion": null, "TerritorialThirdPossesion": null, "Officials": [{"IdCountry": "SUI", "OfficialId": "240087", "NameShort": [{"Locale": "en-GB", "Description": "Esther STAUBLI"}], "Name": [{"Locale": "en-GB", "Description": "STAUBLI Esther"}], "OfficialType": 1, "TypeLocalized": [{"Locale": "en-GB", "Description": "Referee"}]}, {"IdCountry": "ENG", "OfficialId": "301685", "NameShort": [{"Locale": "en-GB", "Description": "Sian MASSEY"}], "Name": [{"Locale": "en-GB", "Description": "MASSEY Sian"}], "OfficialType": 2, "TypeLocalized": [{"Locale": "en-GB", "Description": "Assistant Referee 1"}]}, {"IdCountry": "SUI", "OfficialId": "348388", "NameShort": [{"Locale": "en-GB", "Description": "Susanne KUENG"}], "Name": [{"Locale": "en-GB", "Description": "KUNG Susanne"}], "OfficialType": 3, "TypeLocalized": [{"Locale": "en-GB", "Description": "Assistant Referee 2"}]}, {"IdCountry": "FRA", "OfficialId": "302091", "NameShort": [{"Locale": "en-GB", "Description": "Stephanie FRAPPART"}], "Name": [{"Locale": "en-GB", "Description": "FRAPPART Stephanie"}], "OfficialType": 4, "TypeLocalized": [{"Locale": "en-GB", "Description": "Fourth official"}]}, {"IdCountry": "GER", "OfficialId": "373388", "NameShort": [{"Locale": "en-GB", "Description": "Bastian DANKERT"}], "Name": [{"Locale": "en-GB", "Description": "DANKERT Bastian"}], "OfficialType": 5, "TypeLocalized": [{"Locale": "en-GB", "Description": "Video Assistant Referee (VAR)"}]}, {"IdCountry": "CZE", "OfficialId": "301782", "NameShort": [{"Locale": "en-GB", "Description": "Lucie RATAJOVA"}], "Name": [{"Locale": "en-GB", "Description": "Lucie RATAJOVA"}], "OfficialType": 7, "TypeLocalized": [{"Locale": "en-GB", "Description": "Offside VAR"}, {"Locale": "en-GB", "Description": "Offside VAR"}, {"Locale": "en-GB", "Description": "Offside VAR"}, {"Locale": "en-GB", "Description": "Offside VAR"}]}, {"IdCountry": "GER", "OfficialId": "416008", "NameShort": [{"Locale": "en-GB", "Description": "Sascha STEGEMANN"}], "Name": [{"Locale": "en-GB", "Description": "Sascha STEGEMANN"}], "OfficialType": 8, "TypeLocalized": [{"Locale": "en-GB", "Description": "Assistant VAR"}]}, {"IdCountry": "MAD", "OfficialId": "206952", "NameShort": [{"Locale": "en-GB", "Description": "Lidwine RAKOTOZAFINORO"}], "Name": [{"Locale": "en-GB", "Description": "RAKOTOZAFINORO Lidwine"}], "OfficialType": 10, "TypeLocalized": [{"Locale": "en-GB", "Description": "Reserve Assistant Referee"}]}], "MatchStatus": 0, "GroupName": [{"Locale": "en-GB", "Description": "Group C"}], "StageName": [{"Locale": "en-GB", "Description": "First Stage"}], "OfficialityStatus": 2, "TimeDefined": true, "Properties": {"IdCBS": "300438225", "IdIFES": "118425"}, "IsUpdateable": null}